pyciphersuite/__init__.py
pyciphersuite/api.py
pyciphersuite-0.1.1.dist-info/LICENSE
pyciphersuite-0.1.1.dist-info/METADATA
pyciphersuite-0.1.1.dist-info/WHEEL
pyciphersuite-0.1.1.dist-info/top_level.txt
pyciphersuite-0.1.1.dist-info/RECORD
