Metadata-Version: 2.1
Name: pyciphersuite
Version: 0.1.1
Summary: Python API wrapper for ciphersuiteinfo
Home-page: https://github.com/jxdv/pyciphersuite
Author: jxdv
License: MIT
Keywords: python3,api,rest api,ciphersuite
Platform: UNKNOWN
Classifier: Programming Language :: Python :: 3
Classifier: License :: OSI Approved :: MIT License
License-File: LICENSE
Requires-Dist: requests
